paco/aws/__init__.py
paco/models/__init__.py
paco/models/accounts.py
paco/models/applications.py
paco/models/backup.py
paco/models/base.py
paco/models/cfn_init.py
paco/models/events.py
paco/models/exceptions.py
paco/models/formatter.py
paco/models/gen_vocabulary.py
paco/models/iam.py
paco/models/iot.py
paco/models/loader.py
paco/models/locations.py
paco/models/logging.py
paco/models/metrics.py
paco/models/networks.py
paco/models/project.py
paco/models/references.py
paco/models/reftypes.py
paco/models/registry.py
paco/models/resources.py
paco/models/schemas.py
paco/models/services.py
paco/models/storages.py
paco/models/vocabulary.py
paco/models/yaml.py
paco/models/tests/__init__.py
paco/models/tests/test_loader.py
paco/models/tests/test_references.py
paco.models-7.8.37.dist-info/LICENSE
paco.models-7.8.37.dist-info/METADATA
paco.models-7.8.37.dist-info/WHEEL
paco.models-7.8.37.dist-info/entry_points.txt
paco.models-7.8.37.dist-info/top_level.txt
paco.models-7.8.37.dist-info/RECORD
