Metadata-Version: 2.1
Name: paco.models
Version: 7.8.37
Summary: paco.models: Semantic cloud infrastructure configuration file format and object model
Home-page: https://github.com/waterbear-cloud/paco.models
Author: Waterbear Cloud
Author-email: hello@waterbear.cloud
License: UNKNOWN
Keywords: AWS,Cloud,Infrastructure as Code
Platform: UNKNOWN
Classifier: Programming Language :: Python
Classifier: Programming Language :: Python :: 3.6
Classifier: Programming Language :: Python :: 3.7
Classifier: Programming Language :: Python :: 3.8
Classifier: License :: OSI Approved :: Mozilla Public License 2.0 (MPL 2.0)
Classifier: Development Status :: 5 - Production/Stable
Requires-Dist: Setuptools
Requires-Dist: ruamel.yaml
Requires-Dist: zope.schema
Requires-Dist: troposphere
